pdcli/__init__.py
pdcli/api/__init__.py
pdcli/api/incident.py
pdcli/api/session.py
pdcli/api/user.py
pdcli/cli.py
pdcli/command/__init__.py
pdcli/command/ls.py
pdcli/command/user.py
pdcli/pd.py
python_pdcli-0.1.3.dist-info/entry_points.txt
python_pdcli-0.1.3.dist-info/LICENSE
python_pdcli-0.1.3.dist-info/WHEEL
python_pdcli-0.1.3.dist-info/METADATA
python_pdcli-0.1.3.dist-info/RECORD
