Metadata-Version: 2.1
Name: python-pdcli
Version: 0.1.3
Summary: PD cli
Home-page: https://github.com/koyeung/python-pdcli
Author: King-On Yeung
Author-email: koyeung@gmail.com
Requires-Python: >=3.8,<4.0
Classifier: Programming Language :: Python :: 3
Classifier: Programming Language :: Python :: 3.10
Classifier: Programming Language :: Python :: 3.8
Classifier: Programming Language :: Python :: 3.9
Requires-Dist: fire (>=0.4.0)
Requires-Dist: pdpyras (>=4.4.0)
Project-URL: Repository, https://github.com/koyeung/python-pdcli
